pokerchances/__init__.py
pokerchances/combtypes.py
pokerchances/poker_chances.py
pokerchances/poker_chances2.py
pokerchances-0.0.10.dist-info/METADATA
pokerchances-0.0.10.dist-info/WHEEL
pokerchances-0.0.10.dist-info/top_level.txt
pokerchances-0.0.10.dist-info/RECORD
